{
  "schema": 2,
  "generated_at": "2026-05-14T21:00:35.497Z",
  "channels": [
    {
      "username": "bbcpersian",
      "title": "BBCPersian",
      "last_fetched_at": "2026-05-14T21:00:31.107Z",
      "post_count": 33,
      "media_count": 26,
      "snapshot_path": "channels/bbcpersian/snapshot.json"
    },
    {
      "username": "dwpersian",
      "title": "DW Persian | دویچه وله فارسی",
      "last_fetched_at": "2026-05-14T21:00:31.081Z",
      "post_count": 20,
      "media_count": 5,
      "snapshot_path": "channels/dwpersian/snapshot.json"
    },
    {
      "username": "farsi_iranwire",
      "title": "Iranwire",
      "last_fetched_at": "2026-05-14T21:00:31.022Z",
      "post_count": 27,
      "media_count": 25,
      "snapshot_path": "channels/farsi_iranwire/snapshot.json"
    },
    {
      "username": "farsivoa",
      "title": "Farsi VOA",
      "last_fetched_at": "2026-05-14T21:00:32.578Z",
      "post_count": 33,
      "media_count": 26,
      "snapshot_path": "channels/farsivoa/snapshot.json"
    },
    {
      "username": "hranews",
      "title": "خبرگزاری هرانا",
      "last_fetched_at": "2026-05-14T21:00:32.663Z",
      "post_count": 22,
      "media_count": 10,
      "snapshot_path": "channels/hranews/snapshot.json"
    },
    {
      "username": "iranintltv",
      "title": "Iran International ایران اینترنشنال",
      "last_fetched_at": "2026-05-14T21:00:32.824Z",
      "post_count": 40,
      "media_count": 35,
      "snapshot_path": "channels/iranintltv/snapshot.json"
    },
    {
      "username": "mamlekate",
      "title": "مملکته",
      "last_fetched_at": "2026-05-14T21:00:33.709Z",
      "post_count": 20,
      "media_count": 8,
      "snapshot_path": "channels/mamlekate/snapshot.json"
    },
    {
      "username": "radiofarda",
      "title": "RadioFarda",
      "last_fetched_at": "2026-05-14T21:00:34.081Z",
      "post_count": 27,
      "media_count": 14,
      "snapshot_path": "channels/radiofarda/snapshot.json"
    },
    {
      "username": "sahamnewsorg",
      "title": "سهام نیوز",
      "last_fetched_at": "2026-05-14T21:00:34.170Z",
      "post_count": 24,
      "media_count": 12,
      "snapshot_path": "channels/sahamnewsorg/snapshot.json"
    }
  ]
}
